{
  "checks": {
    "dangerous_flags": false,
    "errors_zero": false,
    "gcp_ok": false,
    "latency_ok": false,
    "ready_ok": false,
    "revs_ok": false
  },
  "cli_id": "M6_G4.01-CR-READY-HARD-GATE-FINAL",
  "describe_path": ".ci/m6/M6_G4.01-CR-READY-HARD-GATE-FINAL/gcp_describe.json",
  "detect": {
    "region": "",
    "service": "",
    "url": "https://agent-data-test-pfne2mqwja-as.a.run.app\""
  },
  "head": "66484ed90aa3c68d61563baed6be67ad3398786c",
  "http_path": ".ci/m6/M6_G4.01-CR-READY-HARD-GATE-FINAL/http_probe.json",
  "pass": false,
  "reason": "latency_p95_too_high_or_probe_failed",
  "scan_path": ".ci/m6/M6_G4.01-CR-READY-HARD-GATE-FINAL/repo_audit.json",
  "ts_utc": "2025-09-01T02:46:13Z"
}
